{
  "metadata": {
    "timestamp": "20260220_134612",
    "posture": "balanceado",
    "tag": "pc9_verification_mild",
    "n_loans": 200
  },
  "pre_state": {
    "n_loans": 200,
    "total_eva": -261505995.04628944,
    "total_rwa": 2238053453.5,
    "total_ead": 1493990320.0,
    "total_capital_release": 100476496.05366954,
    "action_counts": {
      "REESTRUCTURAR": 184,
      "MANTENER": 16
    },
    "hhi_concentration": 0.21299999999999997,
    "_meta": {
      "cols_used": {
        "EVA": "EVA_pre",
        "RWA": "RWA_pre",
        "EAD": "EAD",
        "Action": "Accion_final"
      }
    }
  },
  "micro_proposal": {
    "n_loans": 200,
    "total_eva": 270967086.7235843,
    "total_rwa": 1275270390.4650521,
    "total_ead": 1493990320.0,
    "total_capital_release": 100476496.05366954,
    "action_counts": {
      "REESTRUCTURAR": 184,
      "MANTENER": 16
    },
    "hhi_concentration": 0.21299999999999997,
    "_meta": {
      "cols_used": {
        "EVA": "EVA_post",
        "RWA": "RWA_post",
        "EAD": "EAD",
        "Action": "Accion"
      }
    }
  },
  "final_state": {
    "n_loans": 200,
    "total_eva": 270967086.7235843,
    "total_rwa": 1275270390.4650521,
    "total_ead": 1493990320.0,
    "total_capital_release": 141354297.79650384,
    "action_counts": {
      "REESTRUCTURAR": 100,
      "VENDER": 59,
      "MANTENER": 41
    },
    "hhi_concentration": 0.21299999999999997,
    "_meta": {
      "cols_used": {
        "EVA": "EVA_post",
        "RWA": "RWA_post",
        "EAD": "EAD",
        "Action": "Accion_final"
      }
    }
  },
  "delta_impact": {
    "total_eva": 532473081.76987374,
    "total_rwa": -962783063.0349479,
    "capital_release": 141354297.79650384
  }
}